sawari/__init__.py
sawari/config/file_extensions.txt
sawari/config/iana_mimetypes.txt
sawari/config/mimetypes.txt
sawari/config/nodetypes.txt
sawari/core/__init__.py
sawari/core/argparser.py
sawari/core/comment.py
sawari/core/context.py
sawari/core/html.py
sawari/core/jsparser.py
sawari/core/output.py
sawari/core/url_utils.py
sawari/modes/__init__.py
sawari/modes/inspect.py
sawari/modes/query.py
sawari/modes/strings.py
sawari/modes/tree.py
sawari/modes/urls/__init__.py
sawari/modes/urls/aliases.py
sawari/modes/urls/config.py
sawari/modes/urls/extractor.py
sawari/modes/urls/filters.py
sawari/modes/urls/output.py
sawari/modes/urls/processors.py
sawari/modes/urls/resolvers.py
sawari/modes/urls/symbols.py
sawari/modes/urls/traversal.py
sawari/sawari.py
sawari-1.0.6.dist-info/LICENSE.md
sawari-1.0.6.dist-info/METADATA
sawari-1.0.6.dist-info/WHEEL
sawari-1.0.6.dist-info/entry_points.txt
sawari-1.0.6.dist-info/RECORD
